CHANGELOG.md
nekontrol/compare.py
nekontrol/config.py
nekontrol/interactive/cli.py
nekontrol/interactive/run.py
nekontrol/interactive/spinner.py
nekontrol/language.py
nekontrol/problems.py
nekontrol/util.py
nekontrol-0.2.5.dist-info/METADATA
nekontrol-0.2.5.dist-info/WHEEL
nekontrol-0.2.5.dist-info/entry_points.txt
nekontrol-0.2.5.dist-info/RECORD
