Metadata-Version: 2.1
Name: nekontrol
Version: 0.2.5
Summary: A program for testing kattis solutions with input and output.
Home-page: https://github.com/Quaqqer/nekontrol
Keywords: kattis,competetive programming
Author: Emanuel S
Author-email: emanuel@empa.xyz
Requires-Python: >=3.10,<4.0
Classifier: Programming Language :: Python :: 3
Classifier: Programming Language :: Python :: 3.10
Classifier: Programming Language :: Python :: 3.11
Requires-Dist: appdirs (>=1.4.4,<2.0.0)
Requires-Dist: click (>=8.1.3,<9.0.0)
Requires-Dist: natsort (>=8.2.0,<9.0.0)
Requires-Dist: requests (>=2.28.2,<3.0.0)
Requires-Dist: termcolor (>=2.2.0,<3.0.0)
Project-URL: Repository, https://github.com/Quaqqer/nekontrol
